pycall/__init__.py
pycall/actions.py
pycall/call.py
pycall/callfile.py
pycall/errors.py
pycall-2.3.2.dist-info/DESCRIPTION.rst
pycall-2.3.2.dist-info/METADATA
pycall-2.3.2.dist-info/RECORD
pycall-2.3.2.dist-info/WHEEL
pycall-2.3.2.dist-info/metadata.json
pycall-2.3.2.dist-info/top_level.txt
