Metadata-Version: 1.0
Name: pycall
Version: 2.3.2
Summary: A flexible python library for creating and using Asterisk call files.
Home-page: http://pycall.org/
Author: Randall Degges
Author-email: rdegges@gmail.com
License: UNLICENSE
Keywords: asterisk callfile call file telephony voip
Platform: UNKNOWN
